{
  "id": "kb-2026-05-29-010",
  "title": "deep-learning-drizzle",
  "source": "github-trending",
  "source_id": "kmario23/deep-learning-drizzle",
  "url": "https://github.com/kmario23/deep-learning-drizzle",
  "summary": "An educational repository focused on machine learning, deep learning, and artificial intelligence topics including neural networks, computer vision, reinforcement learning, and natural language proces",
  "tags": [
    "machine-learning\"",
    "\"deep-learning\"",
    "\"reinforcement-learning\"",
    "\"computer-vision\"",
    "\"nlp"
  ],
  "relevance_score": 0.43499999999999994,
  "collected_at": "2018-11-26T01:17:36Z",
  "analyzed_at": "2026-05-29T01:55:23.529303Z",
  "organized_at": "2026-05-29T01:55:35.516087Z",
  "status": "published"
}