{
  "id": "kb-2026-07-21-004",
  "title": "Artificial-Intelligence-Deep-Learning-Machine-Learning-Tutorials",
  "source": "github-trending",
  "source_id": "TarrySingh/Artificial-Intelligence-Deep-Learning-Machine-Learning-Tutorials",
  "url": "https://github.com/TarrySingh/Artificial-Intelligence-Deep-Learning-Machine-Learning-Tutorials",
  "summary": "A comprehensive collection of tutorials covering Deep Learning, Artificial Intelligence, and Machine Learning with practical applications spanning computer vision, natural language processing, and ind",
  "tags": [
    "deep-learning\"",
    "\"machine-learning\"",
    "\"tensorflow\"",
    "\"pytorch\"",
    "\"keras\""
  ],
  "relevance_score": 0.85,
  "collected_at": "2017-07-13T19:46:01Z",
  "analyzed_at": "2026-07-21T01:17:35.092325Z",
  "organized_at": "2026-07-21T01:18:51.949842Z",
  "status": "published"
}