{
  "id": "kb-2026-05-24-009",
  "title": "MachineLearningNotebooks",
  "source": "github-trending",
  "source_id": "Azure/MachineLearningNotebooks",
  "url": "https://github.com/Azure/MachineLearningNotebooks",
  "summary": "Microsoft Azure Machine Learning Python SDK tutorials and examples featuring ML and deep learning notebooks for data scientists and ML engineers using Azure cloud platform.",
  "tags": [
    "machine-learning\"",
    "\"deep-learning\"",
    "\"azure-machine-learning\"",
    "\"python-sdk\"",
    "\"data-science\""
  ],
  "relevance_score": 0.85,
  "collected_at": "2018-08-17T17:29:14Z",
  "analyzed_at": "2026-05-24T01:55:25.811573Z",
  "organized_at": "2026-05-24T01:55:44.082881Z",
  "status": "published"
}