{
  "id": "kb-2026-07-10-004",
  "title": "Artificial-Intelligence-Deep-Learning-Machine-Learning-Tutorials",
  "source": "github-trending",
  "source_id": "TarrySingh/Artificial-Intelligence-Deep-Learning-Machine-Learning-Tutorials",
  "url": "https://github.com/TarrySingh/Artificial-Intelligence-Deep-Learning-Machine-Learning-Tutorials",
  "summary": "A curated collection of comprehensive tutorials and resources covering deep learning, artificial intelligence, and machine learning domains including TensorFlow, PyTorch, Keras, computer vision, NLP, ",
  "tags": [
    "machine-learning\"",
    "\"deep-learning\"",
    "\"tensorflow\"",
    "\"pytorch\"",
    "\"keras\""
  ],
  "relevance_score": 0.5,
  "collected_at": "2017-07-13T19:46:01Z",
  "analyzed_at": "2026-07-10T01:24:19.308043Z",
  "organized_at": "2026-07-10T01:26:01.581478Z",
  "status": "published"
}