{
  "id": "kb-2026-06-03-009",
  "title": "MachineLearningNotebooks",
  "source": "github-trending",
  "source_id": "Azure/MachineLearningNotebooks",
  "url": "https://github.com/Azure/MachineLearningNotebooks",
  "summary": "Official Microsoft repository containing Python notebooks demonstrating machine learning and deep learning workflows using Azure Machine Learning Python SDK. Includes examples for training, deploying,",
  "tags": [
    "machine-learning\"",
    "\"deep-learning\"",
    "\"azure-machine-learning\"",
    "\"python-sdk\"",
    "\"notebooks\""
  ],
  "relevance_score": 0.5,
  "collected_at": "2018-08-17T17:29:14Z",
  "analyzed_at": "2026-06-03T02:29:47.464781Z",
  "organized_at": "2026-06-03T02:30:22.455406Z",
  "status": "published"
}